wl/__init__.py
wl/main.py
wl/paths.py
wl/cli/__init__.py
wl/cli/log.py
wl/cli/parser.py
wl/cli/datatypes/__init__.py
wl/cli/datatypes/dict.py
wl/cli/datatypes/list.py
wl/cli/datatypes/str.py
wl/commands/__init__.py
wl/commands/command.py
wl/commands/config.py
wl/commands/config_get.py
wl/commands/config_path.py
wl/commands/ls.py
wl/commands/registry.py
wl/commands/restore.py
wl/commands/set.py
wl/core/__init__.py
wl/core/wallpapers.py
wl/resources/__init__.py
wl/resources/config.py
wl/resources/fs.py
wl/scripts/__init__.py
wl/scripts/arguments.py
wl_wall-1.0.7.dist-info/LICENSE
wl_wall-1.0.7.dist-info/METADATA
wl_wall-1.0.7.dist-info/WHEEL
wl_wall-1.0.7.dist-info/entry_points.txt
wl_wall-1.0.7.dist-info/top_level.txt
wl_wall-1.0.7.dist-info/RECORD
