Metadata-Version: 2.1
Name: wl-wall
Version: 1.0.7
Summary: A simply cli wallpaper manager for linux
Home-page: UNKNOWN
Author: Gabriel Guerra
Author-email: gfranklings@gmail.com
License: MIT
Keywords: wallpapers,python,managers,cli
Platform: UNKNOWN
Requires-Python: >=3.6
License-File: LICENSE
